{
  "date": "2026-06-17",
  "generated_at": "2026-06-17T17:34:31.500358Z",
  "saude": {
    "hrv": 68,
    "hrv_7d": 38,
    "hrv_status": "balanced",
    "hrv_baseline_low": 33,
    "hrv_baseline_high": 42,
    "rhr": 60,
    "rhr_baseline": null,
    "sono_h": 7.0,
    "sono_score": 80,
    "sono_deep": 1.1,
    "sono_rem": 1.2,
    "sono_awake": 5.0,
    "body_battery": 63,
    "stress_avg": 21,
    "stress_rest": 61.87,
    "atl": 669.0,
    "ctl": 2675.0,
    "tsb": null,
    "acwr": null,
    "load_3d": null,
    "load_aerobic_low": 1748.0,
    "load_aerobic_high": 292.0,
    "load_anaerobic": 635.0,
    "load_total_month": 2675.0,
    "load_target_low": "580–1418",
    "load_target_high": "954–1792",
    "training_status": "Recuperação",
    "fitness_trend": "Estável",
    "training_readiness": null,
    "vo2max": 49.4,
    "peso": null,
    "previsoes": {
      "5K": 1362,
      "10K": 2884,
      "Meia": 6537,
      "Maratona": 14609
    },
    "risco_lesao": "MODERADO",
    "risco_cor": "#FFB800",
    "prova_dias": 88,
    "prova_data": "13/09/2026",
    "prova_fase": "BASE",
    "nutricao": {
      "cho_g_h": 80,
      "cho_total": null,
      "agua_ml_h": 750,
      "agua_total": null,
      "pre_kcal": 350,
      "pos_prot_g": 30,
      "dur_min": 0
    },
    "sono_alvo_h": 8.5,
    "sono_deita": "22:00",
    "sono_deficit_h": 1.5
  },
  "ontem": [
    {
      "mod": "bike",
      "icone": "🚴",
      "nome": "Erkrath eBiking",
      "dist": "11.2km",
      "dur": "38m40s",
      "fc": 112.0,
      "fc_max": 145.0,
      "cal": 290.0,
      "cad": 59.0,
      "tss": null,
      "np": null,
      "swolf": null,
      "aerobic_te": 1.600000023841858,
      "anaerobic_te": 0.0,
      "elev": 192.0,
      "perf": "17.4km/h",
      "pl": "Velocidade",
      "_dist_m": 11243.080078125,
      "_dur_s": 2320.260986328125
    }
  ],
  "hoje": [
    {
      "icone": "🏊",
      "nome": "Swimming  🥽🩲🏊",
      "tipo": "",
      "dur": "—",
      "dist": "—"
    },
    {
      "icone": "🚴",
      "nome": "Easy Ride",
      "tipo": "",
      "dur": "55m00s",
      "dist": "—"
    }
  ],
  "amanha": [
    {
      "icone": "🏊",
      "nome": "Power Through Scull (short)",
      "tipo": "",
      "dur": "—",
      "dist": "—"
    }
  ],
  "hoje_feito": [],
  "semana": {
    "swim_km": 0,
    "swim_min": 0,
    "bike_km": 11.2,
    "bike_min": 38.7,
    "run_km": 6.8,
    "run_min": 38.7,
    "total_tss": 0.0,
    "n_treinos": 3
  },
  "semana_passada": {
    "swim_km": 5.5,
    "swim_min": 133.0,
    "bike_km": 1.1,
    "bike_min": 7.1,
    "run_km": 13.2,
    "run_min": 85.7
  },
  "clima": {
    "temp_max": 26.3,
    "temp_min": 15.6,
    "chuva_pct": 20,
    "vento_kmh": 13.0,
    "temp_atual": 25.8,
    "emoji": "🌧️"
  },
  "hrv_7dias": [
    {
      "date": "2026-06-11",
      "value": 60.0
    },
    {
      "date": "2026-06-12",
      "value": 52.0
    },
    {
      "date": "2026-06-13",
      "value": 53.0
    },
    {
      "date": "2026-06-14",
      "value": 38.0
    },
    {
      "date": "2026-06-15",
      "value": 70.0
    },
    {
      "date": "2026-06-16",
      "value": 62.0
    },
    {
      "date": "2026-06-17",
      "value": 68.0
    }
  ],
  "vo2max_hist": [
    {
      "date": "2026-06-03",
      "value": 49.4
    },
    {
      "date": "2026-06-04",
      "value": 49.4
    },
    {
      "date": "2026-06-05",
      "value": 49.4
    },
    {
      "date": "2026-06-06",
      "value": 49.2
    },
    {
      "date": "2026-06-07",
      "value": 49.2
    },
    {
      "date": "2026-06-08",
      "value": 49.2
    },
    {
      "date": "2026-06-09",
      "value": 49.2
    },
    {
      "date": "2026-06-10",
      "value": 49.2
    },
    {
      "date": "2026-06-11",
      "value": 49.4
    },
    {
      "date": "2026-06-12",
      "value": 49.4
    },
    {
      "date": "2026-06-13",
      "value": 49.4
    },
    {
      "date": "2026-06-14",
      "value": 49.4
    },
    {
      "date": "2026-06-15",
      "value": 49.4
    },
    {
      "date": "2026-06-16",
      "value": 49.4
    },
    {
      "date": "2026-06-17",
      "value": 49.4
    }
  ],
  "prs": [],
  "sono_performance": [
    {
      "date": "2026-06-04",
      "sono": 7.2,
      "te": 3.6
    },
    {
      "date": "2026-06-05",
      "sono": 5.0,
      "te": 3.2
    },
    {
      "date": "2026-06-06",
      "sono": 7.4,
      "te": 3.0
    },
    {
      "date": "2026-06-07",
      "sono": 6.0,
      "te": 3.7
    },
    {
      "date": "2026-06-08",
      "sono": 7.8,
      "te": 1.5
    },
    {
      "date": "2026-06-09",
      "sono": 6.8,
      "te": 2.8
    },
    {
      "date": "2026-06-10",
      "sono": 7.0,
      "te": 2.7
    },
    {
      "date": "2026-06-11",
      "sono": 7.6,
      "te": 3.3
    },
    {
      "date": "2026-06-12",
      "sono": 7.5,
      "te": 2.0
    },
    {
      "date": "2026-06-13",
      "sono": 6.0,
      "te": 2.3
    },
    {
      "date": "2026-06-14",
      "sono": 4.4,
      "te": 0.3
    },
    {
      "date": "2026-06-15",
      "sono": 7.3,
      "te": 3.0
    },
    {
      "date": "2026-06-16",
      "sono": 6.2,
      "te": 1.6
    }
  ],
  "insights": {
    "frase": "HRV em alta: execute com precisão, não com intensidade.",
    "sec_readiness": "HRV de 68ms está 30ms acima da média de 7 dias (38ms) e supera o baseline de 33–42ms — sinal claro de recuperação efetiva do SNC. RHR em 60bpm sem baseline definido, mas alinhado ao contexto de recuperação. Sono de 7.0h com score 80 é adequado, porém há déficit de 1.5h em relação à meta; deep sleep em 1.1h e REM em 1.2h indicam qualidade razoável. Body Battery de 63/100 com stress médio de 21 confirma janela positiva para treino aeróbico leve.",
    "sec_treino_ontem": "O eBike em Erkrath (11.2km, 38min40s, 17.4km/h) foi de baixíssimo impacto fisiológico — FC média de 112bpm e TE aeróbico de 1.6 indicam estímulo insuficiente para adaptação aeróbica. Cadência de 59rpm está abaixo do ideal para ciclismo (80–90rpm), sugerindo pedalada menos eficiente ou terreno exigente. Treino válido como recuperação ativa, sem relevância para progressão de carga.",
    "sec_carga": "Z1 em 1748 ultrapassa o teto do target (580–1418), indicando excesso de volume aeróbico leve sem correspondência em Z2 (292 vs target 954–1792) — distribuição invertida e crítica para fase BASE. Z3+ em 635 está elevado proporcionalmente ao volume total de Z2, criando polarização inadequada. Risco de lesão MODERADO e CTL/ATL desbalanceados reforçam necessidade urgente de reequilibrar zonas nas próximas semanas.",
    "sec_hoje": "Treino planejado: natação (Swimming) + Easy Ride de 55 minutos — nenhum ainda executado. Para a natação, foco em volume aeróbico Z1-Z2, FC aquática não excedendo 140bpm. O Easy Ride de 55min deve ser executado com FC controlada entre 120–140bpm (Z1-Z2), cadência-alvo 85–90rpm, sem esforços acima de Z2 — o objetivo é estimular Z2 deficitário sem comprometer a recuperação.",
    "sec_ajuste": "Easy Ride: manter 55min com FC teto de 140bpm, 100% em Z1-Z2, cadência 85–90rpm, potência alvo 140–170W se disponível. Natação: volume entre 1500–2000m em ritmo aeróbico leve, sem sprints.",
    "sec_alertas": "Z2 criticamente abaixo do target mensal (292 vs mínimo 954) — cada sessão fácil deve priorizar Z2 real, não Z1 passivo. Evitar armadilha de volume fácil excessivo sem estímulo aeróbico efetivo.",
    "sec_nutricao": "Pré-treino: 350kcal com carboidrato de baixo-médio índice glicêmico 60min antes (banana + aveia). Durante o Easy Ride de 55min: 500ml de água com eletrólitos, sem necessidade de gel abaixo de 60min; pós-treino: 30g de proteína em até 30min (whey ou equivalente) + 40–60g de CHO para reposição.",
    "status_readiness": "BOM",
    "status_carga": "SUAVE",
    "acao_hoje": "MANTER",
    "analise_hoje": "Dia de dupla leve (natação + bike 55min) com readiness favorável — janela ideal para corrigir déficit de Z2 sem acumular fadiga. Execução disciplinada nas zonas é mais importante que duração.",
    "alerta": "Z2 mensal em apenas 292 de um mínimo de 954 — base aeróbica comprometida se padrão persistir.",
    "treino_forca": [
      {
        "exercicio": "Agachamento Goblet",
        "series": 3,
        "repeticoes": "12-15",
        "carga": "moderada",
        "foco": "Fortalece glúteos e quadríceps, base de potência na pedalada e corrida 70.3"
      },
      {
        "exercicio": "Ponte de Glúteo Unilateral",
        "series": 3,
        "repeticoes": "10-12",
        "carga": "leve",
        "foco": "Ativa glúteo médio e corrige assimetrias posturais críticas na corrida"
      },
      {
        "exercicio": "Prancha Lateral com Abdução de Quadril",
        "series": 3,
        "repeticoes": "30s",
        "carga": "leve",
        "foco": "Estabilidade de core lateral, essencial para economia de corrida no 70.3"
      },
      {
        "exercicio": "Remada com Halteres (Unilateral)",
        "series": 3,
        "repeticoes": "10-12",
        "carga": "moderada",
        "foco": "Fortalece dorsais e romboides, sustentando posição aerodinâmica no ciclismo"
      },
      {
        "exercicio": "Afundo Reverso com Joelho Elevado",
        "series": 3,
        "repeticoes": "10",
        "carga": "moderada",
        "foco": "Força funcional unilateral e equilíbrio, reduz risco de lesão na corrida"
      },
      {
        "exercicio": "Dead Bug (Core Antiextensão)",
        "series": 3,
        "repeticoes": "8-10",
        "carga": "leve",
        "foco": "Core profundo e estabilidade lombar, protege coluna em esforços prolongados"
      },
      {
        "exercicio": "Mobilidade de Quadril — 90/90 Stretch",
        "series": 2,
        "repeticoes": "60s",
        "carga": "leve",
        "foco": "Aumenta amplitude de quadril, melhora passada na corrida e posição no bike"
      }
    ]
  }
}